{
  "id": "6a4e14ed-3021-4d60-b298-c5c56cf2ecff",
  "prevId": "e658dc7b-2664-46b4-b755-d09cc086d1a7",
  "version": "5",
  "dialect": "pg",
  "tables": {
    "audit_logs": {
      "name": "audit_logs",
      "schema": "",
      "columns": {
        "id": {
          "name": "id",
          "type": "serial",
          "primaryKey": true,
          "notNull": true
        },
        "actor_user_id": {
          "name": "actor_user_id",
          "type": "integer",
          "primaryKey": false,
          "notNull": false
        },
        "action": {
          "name": "action",
          "type": "varchar(128)",
          "primaryKey": false,
          "notNull": true
        },
        "resource_type": {
          "name": "resource_type",
          "type": "varchar(64)",
          "primaryKey": false,
          "notNull": true
        },
        "resource_id": {
          "name": "resource_id",
          "type": "integer",
          "primaryKey": false,
          "notNull": false
        },
        "data": {
          "name": "data",
          "type": "jsonb",
          "primaryKey": false,
          "notNull": true,
          "default": "'{}'"
        },
        "created_at": {
          "name": "created_at",
          "type": "timestamp",
          "primaryKey": false,
          "notNull": true,
          "default": "now()"
        }
      },
      "indexes": {},
      "foreignKeys": {
        "audit_logs_actor_user_id_users_id_fk": {
          "name": "audit_logs_actor_user_id_users_id_fk",
          "tableFrom": "audit_logs",
          "tableTo": "users",
          "columnsFrom": [
            "actor_user_id"
          ],
          "columnsTo": [
            "id"
          ],
          "onDelete": "no action",
          "onUpdate": "no action"
        }
      },
      "compositePrimaryKeys": {},
      "uniqueConstraints": {}
    },
    "clubs": {
      "name": "clubs",
      "schema": "",
      "columns": {
        "id": {
          "name": "id",
          "type": "serial",
          "primaryKey": true,
          "notNull": true
        },
        "owner_user_id": {
          "name": "owner_user_id",
          "type": "integer",
          "primaryKey": false,
          "notNull": true
        },
        "name": {
          "name": "name",
          "type": "varchar(200)",
          "primaryKey": false,
          "notNull": true
        },
        "description": {
          "name": "description",
          "type": "text",
          "primaryKey": false,
          "notNull": true,
          "default": "''"
        },
        "location": {
          "name": "location",
          "type": "jsonb",
          "primaryKey": false,
          "notNull": false
        },
        "address": {
          "name": "address",
          "type": "text",
          "primaryKey": false,
          "notNull": false
        },
        "amenities": {
          "name": "amenities",
          "type": "jsonb",
          "primaryKey": false,
          "notNull": true,
          "default": "'[]'"
        },
        "verified": {
          "name": "verified",
          "type": "boolean",
          "primaryKey": false,
          "notNull": true,
          "default": false
        }
      },
      "indexes": {},
      "foreignKeys": {
        "clubs_owner_user_id_users_id_fk": {
          "name": "clubs_owner_user_id_users_id_fk",
          "tableFrom": "clubs",
          "tableTo": "users",
          "columnsFrom": [
            "owner_user_id"
          ],
          "columnsTo": [
            "id"
          ],
          "onDelete": "no action",
          "onUpdate": "no action"
        }
      },
      "compositePrimaryKeys": {},
      "uniqueConstraints": {}
    },
    "consents": {
      "name": "consents",
      "schema": "",
      "columns": {
        "id": {
          "name": "id",
          "type": "serial",
          "primaryKey": true,
          "notNull": true
        },
        "user_id": {
          "name": "user_id",
          "type": "integer",
          "primaryKey": false,
          "notNull": true
        },
        "policy": {
          "name": "policy",
          "type": "varchar(128)",
          "primaryKey": false,
          "notNull": true
        },
        "version": {
          "name": "version",
          "type": "varchar(64)",
          "primaryKey": false,
          "notNull": true
        },
        "accepted_at": {
          "name": "accepted_at",
          "type": "timestamp",
          "primaryKey": false,
          "notNull": true,
          "default": "now()"
        }
      },
      "indexes": {},
      "foreignKeys": {
        "consents_user_id_users_id_fk": {
          "name": "consents_user_id_users_id_fk",
          "tableFrom": "consents",
          "tableTo": "users",
          "columnsFrom": [
            "user_id"
          ],
          "columnsTo": [
            "id"
          ],
          "onDelete": "no action",
          "onUpdate": "no action"
        }
      },
      "compositePrimaryKeys": {},
      "uniqueConstraints": {}
    },
    "entitlements": {
      "name": "entitlements",
      "schema": "",
      "columns": {
        "user_id": {
          "name": "user_id",
          "type": "integer",
          "primaryKey": false,
          "notNull": true
        },
        "feature": {
          "name": "feature",
          "type": "varchar(128)",
          "primaryKey": false,
          "notNull": true
        },
        "active": {
          "name": "active",
          "type": "boolean",
          "primaryKey": false,
          "notNull": true,
          "default": false
        },
        "source": {
          "name": "source",
          "type": "varchar(128)",
          "primaryKey": false,
          "notNull": true,
          "default": "'stripe'"
        }
      },
      "indexes": {},
      "foreignKeys": {
        "entitlements_user_id_users_id_fk": {
          "name": "entitlements_user_id_users_id_fk",
          "tableFrom": "entitlements",
          "tableTo": "users",
          "columnsFrom": [
            "user_id"
          ],
          "columnsTo": [
            "id"
          ],
          "onDelete": "no action",
          "onUpdate": "no action"
        }
      },
      "compositePrimaryKeys": {
        "entitlements_user_id_feature_pk": {
          "name": "entitlements_user_id_feature_pk",
          "columns": [
            "user_id",
            "feature"
          ]
        }
      },
      "uniqueConstraints": {}
    },
    "events": {
      "name": "events",
      "schema": "",
      "columns": {
        "id": {
          "name": "id",
          "type": "serial",
          "primaryKey": true,
          "notNull": true
        },
        "creator_type": {
          "name": "creator_type",
          "type": "varchar(32)",
          "primaryKey": false,
          "notNull": true
        },
        "creator_id": {
          "name": "creator_id",
          "type": "integer",
          "primaryKey": false,
          "notNull": true
        },
        "club_id": {
          "name": "club_id",
          "type": "integer",
          "primaryKey": false,
          "notNull": false
        },
        "title": {
          "name": "title",
          "type": "varchar(250)",
          "primaryKey": false,
          "notNull": true
        },
        "description": {
          "name": "description",
          "type": "text",
          "primaryKey": false,
          "notNull": true,
          "default": "''"
        },
        "starts_at": {
          "name": "starts_at",
          "type": "timestamp",
          "primaryKey": false,
          "notNull": true
        },
        "ends_at": {
          "name": "ends_at",
          "type": "timestamp",
          "primaryKey": false,
          "notNull": false
        },
        "location_mode": {
          "name": "location_mode",
          "type": "varchar(32)",
          "primaryKey": false,
          "notNull": true
        },
        "custom_location": {
          "name": "custom_location",
          "type": "jsonb",
          "primaryKey": false,
          "notNull": false
        },
        "capacity": {
          "name": "capacity",
          "type": "integer",
          "primaryKey": false,
          "notNull": false
        },
        "privacy": {
          "name": "privacy",
          "type": "varchar(32)",
          "primaryKey": false,
          "notNull": true,
          "default": "'public'"
        },
        "ticketed": {
          "name": "ticketed",
          "type": "boolean",
          "primaryKey": false,
          "notNull": true,
          "default": false
        },
        "price_cents": {
          "name": "price_cents",
          "type": "integer",
          "primaryKey": false,
          "notNull": false
        }
      },
      "indexes": {},
      "foreignKeys": {
        "events_club_id_clubs_id_fk": {
          "name": "events_club_id_clubs_id_fk",
          "tableFrom": "events",
          "tableTo": "clubs",
          "columnsFrom": [
            "club_id"
          ],
          "columnsTo": [
            "id"
          ],
          "onDelete": "no action",
          "onUpdate": "no action"
        }
      },
      "compositePrimaryKeys": {},
      "uniqueConstraints": {}
    },
    "matches": {
      "name": "matches",
      "schema": "",
      "columns": {
        "id": {
          "name": "id",
          "type": "serial",
          "primaryKey": true,
          "notNull": true
        },
        "user_a_id": {
          "name": "user_a_id",
          "type": "integer",
          "primaryKey": false,
          "notNull": true
        },
        "user_b_id": {
          "name": "user_b_id",
          "type": "integer",
          "primaryKey": false,
          "notNull": true
        },
        "algo": {
          "name": "algo",
          "type": "varchar(32)",
          "primaryKey": false,
          "notNull": true,
          "default": "'random'"
        },
        "score": {
          "name": "score",
          "type": "integer",
          "primaryKey": false,
          "notNull": false
        },
        "status": {
          "name": "status",
          "type": "varchar(32)",
          "primaryKey": false,
          "notNull": true,
          "default": "'pending'"
        },
        "created_at": {
          "name": "created_at",
          "type": "timestamp",
          "primaryKey": false,
          "notNull": true,
          "default": "now()"
        }
      },
      "indexes": {},
      "foreignKeys": {
        "matches_user_a_id_users_id_fk": {
          "name": "matches_user_a_id_users_id_fk",
          "tableFrom": "matches",
          "tableTo": "users",
          "columnsFrom": [
            "user_a_id"
          ],
          "columnsTo": [
            "id"
          ],
          "onDelete": "no action",
          "onUpdate": "no action"
        },
        "matches_user_b_id_users_id_fk": {
          "name": "matches_user_b_id_users_id_fk",
          "tableFrom": "matches",
          "tableTo": "users",
          "columnsFrom": [
            "user_b_id"
          ],
          "columnsTo": [
            "id"
          ],
          "onDelete": "no action",
          "onUpdate": "no action"
        }
      },
      "compositePrimaryKeys": {},
      "uniqueConstraints": {}
    },
    "messages": {
      "name": "messages",
      "schema": "",
      "columns": {
        "id": {
          "name": "id",
          "type": "serial",
          "primaryKey": true,
          "notNull": true
        },
        "thread_id": {
          "name": "thread_id",
          "type": "integer",
          "primaryKey": false,
          "notNull": true
        },
        "sender_id": {
          "name": "sender_id",
          "type": "integer",
          "primaryKey": false,
          "notNull": true
        },
        "encrypted_payload": {
          "name": "encrypted_payload",
          "type": "text",
          "primaryKey": false,
          "notNull": true
        },
        "created_at": {
          "name": "created_at",
          "type": "timestamp",
          "primaryKey": false,
          "notNull": true,
          "default": "now()"
        }
      },
      "indexes": {},
      "foreignKeys": {
        "messages_thread_id_threads_id_fk": {
          "name": "messages_thread_id_threads_id_fk",
          "tableFrom": "messages",
          "tableTo": "threads",
          "columnsFrom": [
            "thread_id"
          ],
          "columnsTo": [
            "id"
          ],
          "onDelete": "no action",
          "onUpdate": "no action"
        },
        "messages_sender_id_users_id_fk": {
          "name": "messages_sender_id_users_id_fk",
          "tableFrom": "messages",
          "tableTo": "users",
          "columnsFrom": [
            "sender_id"
          ],
          "columnsTo": [
            "id"
          ],
          "onDelete": "no action",
          "onUpdate": "no action"
        }
      },
      "compositePrimaryKeys": {},
      "uniqueConstraints": {}
    },
    "notifications": {
      "name": "notifications",
      "schema": "",
      "columns": {
        "id": {
          "name": "id",
          "type": "serial",
          "primaryKey": true,
          "notNull": true
        },
        "user_id": {
          "name": "user_id",
          "type": "integer",
          "primaryKey": false,
          "notNull": true
        },
        "type": {
          "name": "type",
          "type": "varchar(128)",
          "primaryKey": false,
          "notNull": true
        },
        "payload": {
          "name": "payload",
          "type": "jsonb",
          "primaryKey": false,
          "notNull": true,
          "default": "'{}'"
        },
        "created_at": {
          "name": "created_at",
          "type": "timestamp",
          "primaryKey": false,
          "notNull": true,
          "default": "now()"
        },
        "read_at": {
          "name": "read_at",
          "type": "timestamp",
          "primaryKey": false,
          "notNull": false
        }
      },
      "indexes": {},
      "foreignKeys": {
        "notifications_user_id_users_id_fk": {
          "name": "notifications_user_id_users_id_fk",
          "tableFrom": "notifications",
          "tableTo": "users",
          "columnsFrom": [
            "user_id"
          ],
          "columnsTo": [
            "id"
          ],
          "onDelete": "no action",
          "onUpdate": "no action"
        }
      },
      "compositePrimaryKeys": {},
      "uniqueConstraints": {}
    },
    "order_items": {
      "name": "order_items",
      "schema": "",
      "columns": {
        "id": {
          "name": "id",
          "type": "serial",
          "primaryKey": true,
          "notNull": true
        },
        "order_id": {
          "name": "order_id",
          "type": "integer",
          "primaryKey": false,
          "notNull": true
        },
        "product_id": {
          "name": "product_id",
          "type": "integer",
          "primaryKey": false,
          "notNull": true
        },
        "shop_id": {
          "name": "shop_id",
          "type": "integer",
          "primaryKey": false,
          "notNull": true
        },
        "qty": {
          "name": "qty",
          "type": "integer",
          "primaryKey": false,
          "notNull": true,
          "default": 1
        },
        "unit_price_cents": {
          "name": "unit_price_cents",
          "type": "integer",
          "primaryKey": false,
          "notNull": true
        },
        "fee_cents": {
          "name": "fee_cents",
          "type": "integer",
          "primaryKey": false,
          "notNull": true,
          "default": 0
        }
      },
      "indexes": {},
      "foreignKeys": {
        "order_items_order_id_orders_id_fk": {
          "name": "order_items_order_id_orders_id_fk",
          "tableFrom": "order_items",
          "tableTo": "orders",
          "columnsFrom": [
            "order_id"
          ],
          "columnsTo": [
            "id"
          ],
          "onDelete": "no action",
          "onUpdate": "no action"
        },
        "order_items_product_id_products_id_fk": {
          "name": "order_items_product_id_products_id_fk",
          "tableFrom": "order_items",
          "tableTo": "products",
          "columnsFrom": [
            "product_id"
          ],
          "columnsTo": [
            "id"
          ],
          "onDelete": "no action",
          "onUpdate": "no action"
        },
        "order_items_shop_id_shops_id_fk": {
          "name": "order_items_shop_id_shops_id_fk",
          "tableFrom": "order_items",
          "tableTo": "shops",
          "columnsFrom": [
            "shop_id"
          ],
          "columnsTo": [
            "id"
          ],
          "onDelete": "no action",
          "onUpdate": "no action"
        }
      },
      "compositePrimaryKeys": {},
      "uniqueConstraints": {}
    },
    "orders": {
      "name": "orders",
      "schema": "",
      "columns": {
        "id": {
          "name": "id",
          "type": "serial",
          "primaryKey": true,
          "notNull": true
        },
        "buyer_user_id": {
          "name": "buyer_user_id",
          "type": "integer",
          "primaryKey": false,
          "notNull": true
        },
        "status": {
          "name": "status",
          "type": "order_status",
          "primaryKey": false,
          "notNull": true,
          "default": "'pending'"
        },
        "payment_intent_id": {
          "name": "payment_intent_id",
          "type": "varchar(191)",
          "primaryKey": false,
          "notNull": false
        },
        "total_cents": {
          "name": "total_cents",
          "type": "integer",
          "primaryKey": false,
          "notNull": true,
          "default": 0
        },
        "platform_fee_cents": {
          "name": "platform_fee_cents",
          "type": "integer",
          "primaryKey": false,
          "notNull": true,
          "default": 0
        },
        "created_at": {
          "name": "created_at",
          "type": "timestamp",
          "primaryKey": false,
          "notNull": true,
          "default": "now()"
        }
      },
      "indexes": {},
      "foreignKeys": {
        "orders_buyer_user_id_users_id_fk": {
          "name": "orders_buyer_user_id_users_id_fk",
          "tableFrom": "orders",
          "tableTo": "users",
          "columnsFrom": [
            "buyer_user_id"
          ],
          "columnsTo": [
            "id"
          ],
          "onDelete": "no action",
          "onUpdate": "no action"
        }
      },
      "compositePrimaryKeys": {},
      "uniqueConstraints": {}
    },
    "payouts": {
      "name": "payouts",
      "schema": "",
      "columns": {
        "id": {
          "name": "id",
          "type": "serial",
          "primaryKey": true,
          "notNull": true
        },
        "shop_id": {
          "name": "shop_id",
          "type": "integer",
          "primaryKey": false,
          "notNull": true
        },
        "stripe_transfer_id": {
          "name": "stripe_transfer_id",
          "type": "varchar(191)",
          "primaryKey": false,
          "notNull": false
        },
        "amount_cents": {
          "name": "amount_cents",
          "type": "integer",
          "primaryKey": false,
          "notNull": true,
          "default": 0
        },
        "status": {
          "name": "status",
          "type": "varchar(32)",
          "primaryKey": false,
          "notNull": true,
          "default": "'pending'"
        },
        "period_ref": {
          "name": "period_ref",
          "type": "varchar(64)",
          "primaryKey": false,
          "notNull": false
        }
      },
      "indexes": {},
      "foreignKeys": {
        "payouts_shop_id_shops_id_fk": {
          "name": "payouts_shop_id_shops_id_fk",
          "tableFrom": "payouts",
          "tableTo": "shops",
          "columnsFrom": [
            "shop_id"
          ],
          "columnsTo": [
            "id"
          ],
          "onDelete": "no action",
          "onUpdate": "no action"
        }
      },
      "compositePrimaryKeys": {},
      "uniqueConstraints": {}
    },
    "photos": {
      "name": "photos",
      "schema": "",
      "columns": {
        "id": {
          "name": "id",
          "type": "serial",
          "primaryKey": true,
          "notNull": true
        },
        "user_id": {
          "name": "user_id",
          "type": "integer",
          "primaryKey": false,
          "notNull": true
        },
        "url": {
          "name": "url",
          "type": "text",
          "primaryKey": false,
          "notNull": true
        },
        "is_private": {
          "name": "is_private",
          "type": "boolean",
          "primaryKey": false,
          "notNull": true,
          "default": false
        },
        "is_primary": {
          "name": "is_primary",
          "type": "boolean",
          "primaryKey": false,
          "notNull": true,
          "default": false
        },
        "moderation_status": {
          "name": "moderation_status",
          "type": "moderation_status",
          "primaryKey": false,
          "notNull": true,
          "default": "'pending'"
        },
        "csam_scan_status": {
          "name": "csam_scan_status",
          "type": "csam_scan_status",
          "primaryKey": false,
          "notNull": true,
          "default": "'pending'"
        },
        "created_at": {
          "name": "created_at",
          "type": "timestamp",
          "primaryKey": false,
          "notNull": true,
          "default": "now()"
        }
      },
      "indexes": {},
      "foreignKeys": {
        "photos_user_id_users_id_fk": {
          "name": "photos_user_id_users_id_fk",
          "tableFrom": "photos",
          "tableTo": "users",
          "columnsFrom": [
            "user_id"
          ],
          "columnsTo": [
            "id"
          ],
          "onDelete": "no action",
          "onUpdate": "no action"
        }
      },
      "compositePrimaryKeys": {},
      "uniqueConstraints": {}
    },
    "products": {
      "name": "products",
      "schema": "",
      "columns": {
        "id": {
          "name": "id",
          "type": "serial",
          "primaryKey": true,
          "notNull": true
        },
        "shop_id": {
          "name": "shop_id",
          "type": "integer",
          "primaryKey": false,
          "notNull": true
        },
        "title": {
          "name": "title",
          "type": "varchar(250)",
          "primaryKey": false,
          "notNull": true
        },
        "description": {
          "name": "description",
          "type": "text",
          "primaryKey": false,
          "notNull": true,
          "default": "''"
        },
        "images": {
          "name": "images",
          "type": "jsonb",
          "primaryKey": false,
          "notNull": true,
          "default": "'[]'"
        },
        "price_cents": {
          "name": "price_cents",
          "type": "integer",
          "primaryKey": false,
          "notNull": true
        },
        "currency": {
          "name": "currency",
          "type": "varchar(8)",
          "primaryKey": false,
          "notNull": true,
          "default": "'EUR'"
        },
        "category": {
          "name": "category",
          "type": "varchar(128)",
          "primaryKey": false,
          "notNull": true
        },
        "stock": {
          "name": "stock",
          "type": "integer",
          "primaryKey": false,
          "notNull": true,
          "default": 0
        },
        "age_restricted": {
          "name": "age_restricted",
          "type": "boolean",
          "primaryKey": false,
          "notNull": true,
          "default": true
        },
        "moderation_status": {
          "name": "moderation_status",
          "type": "moderation_status",
          "primaryKey": false,
          "notNull": true,
          "default": "'pending'"
        },
        "active": {
          "name": "active",
          "type": "boolean",
          "primaryKey": false,
          "notNull": true,
          "default": true
        }
      },
      "indexes": {},
      "foreignKeys": {
        "products_shop_id_shops_id_fk": {
          "name": "products_shop_id_shops_id_fk",
          "tableFrom": "products",
          "tableTo": "shops",
          "columnsFrom": [
            "shop_id"
          ],
          "columnsTo": [
            "id"
          ],
          "onDelete": "no action",
          "onUpdate": "no action"
        }
      },
      "compositePrimaryKeys": {},
      "uniqueConstraints": {}
    },
    "profiles": {
      "name": "profiles",
      "schema": "",
      "columns": {
        "user_id": {
          "name": "user_id",
          "type": "integer",
          "primaryKey": true,
          "notNull": true
        },
        "bio": {
          "name": "bio",
          "type": "text",
          "primaryKey": false,
          "notNull": true,
          "default": "''"
        },
        "preferences": {
          "name": "preferences",
          "type": "jsonb",
          "primaryKey": false,
          "notNull": true,
          "default": "'{}'"
        },
        "interests": {
          "name": "interests",
          "type": "jsonb",
          "primaryKey": false,
          "notNull": true,
          "default": "'[]'"
        },
        "boundaries": {
          "name": "boundaries",
          "type": "jsonb",
          "primaryKey": false,
          "notNull": true,
          "default": "'[]'"
        },
        "approx_location": {
          "name": "approx_location",
          "type": "jsonb",
          "primaryKey": false,
          "notNull": false
        },
        "real_location": {
          "name": "real_location",
          "type": "text",
          "primaryKey": false,
          "notNull": false
        },
        "visibility_settings": {
          "name": "visibility_settings",
          "type": "jsonb",
          "primaryKey": false,
          "notNull": true,
          "default": "'{}'"
        }
      },
      "indexes": {},
      "foreignKeys": {
        "profiles_user_id_users_id_fk": {
          "name": "profiles_user_id_users_id_fk",
          "tableFrom": "profiles",
          "tableTo": "users",
          "columnsFrom": [
            "user_id"
          ],
          "columnsTo": [
            "id"
          ],
          "onDelete": "no action",
          "onUpdate": "no action"
        }
      },
      "compositePrimaryKeys": {},
      "uniqueConstraints": {}
    },
    "push_subscriptions": {
      "name": "push_subscriptions",
      "schema": "",
      "columns": {
        "id": {
          "name": "id",
          "type": "serial",
          "primaryKey": true,
          "notNull": true
        },
        "user_id": {
          "name": "user_id",
          "type": "integer",
          "primaryKey": false,
          "notNull": true
        },
        "platform": {
          "name": "platform",
          "type": "push_platform",
          "primaryKey": false,
          "notNull": true,
          "default": "'web'"
        },
        "endpoint": {
          "name": "endpoint",
          "type": "text",
          "primaryKey": false,
          "notNull": true
        },
        "p256dh": {
          "name": "p256dh",
          "type": "text",
          "primaryKey": false,
          "notNull": false
        },
        "auth": {
          "name": "auth",
          "type": "text",
          "primaryKey": false,
          "notNull": false
        },
        "created_at": {
          "name": "created_at",
          "type": "timestamp",
          "primaryKey": false,
          "notNull": true,
          "default": "now()"
        }
      },
      "indexes": {},
      "foreignKeys": {
        "push_subscriptions_user_id_users_id_fk": {
          "name": "push_subscriptions_user_id_users_id_fk",
          "tableFrom": "push_subscriptions",
          "tableTo": "users",
          "columnsFrom": [
            "user_id"
          ],
          "columnsTo": [
            "id"
          ],
          "onDelete": "no action",
          "onUpdate": "no action"
        }
      },
      "compositePrimaryKeys": {},
      "uniqueConstraints": {
        "push_subscriptions_endpoint_unique": {
          "name": "push_subscriptions_endpoint_unique",
          "nullsNotDistinct": false,
          "columns": [
            "endpoint"
          ]
        }
      }
    },
    "quiz_results": {
      "name": "quiz_results",
      "schema": "",
      "columns": {
        "id": {
          "name": "id",
          "type": "serial",
          "primaryKey": true,
          "notNull": true
        },
        "user_id": {
          "name": "user_id",
          "type": "integer",
          "primaryKey": false,
          "notNull": true
        },
        "quiz_version": {
          "name": "quiz_version",
          "type": "varchar(64)",
          "primaryKey": false,
          "notNull": true
        },
        "account_type_at_time": {
          "name": "account_type_at_time",
          "type": "varchar(32)",
          "primaryKey": false,
          "notNull": true
        },
        "answers": {
          "name": "answers",
          "type": "jsonb",
          "primaryKey": false,
          "notNull": true,
          "default": "'[]'"
        },
        "derived_tags": {
          "name": "derived_tags",
          "type": "jsonb",
          "primaryKey": false,
          "notNull": true,
          "default": "'[]'"
        },
        "archetype": {
          "name": "archetype",
          "type": "varchar(128)",
          "primaryKey": false,
          "notNull": false
        },
        "created_at": {
          "name": "created_at",
          "type": "timestamp",
          "primaryKey": false,
          "notNull": true,
          "default": "now()"
        }
      },
      "indexes": {},
      "foreignKeys": {
        "quiz_results_user_id_users_id_fk": {
          "name": "quiz_results_user_id_users_id_fk",
          "tableFrom": "quiz_results",
          "tableTo": "users",
          "columnsFrom": [
            "user_id"
          ],
          "columnsTo": [
            "id"
          ],
          "onDelete": "no action",
          "onUpdate": "no action"
        }
      },
      "compositePrimaryKeys": {},
      "uniqueConstraints": {}
    },
    "reports": {
      "name": "reports",
      "schema": "",
      "columns": {
        "id": {
          "name": "id",
          "type": "serial",
          "primaryKey": true,
          "notNull": true
        },
        "reporter_user_id": {
          "name": "reporter_user_id",
          "type": "integer",
          "primaryKey": false,
          "notNull": false
        },
        "target_type": {
          "name": "target_type",
          "type": "varchar(64)",
          "primaryKey": false,
          "notNull": true
        },
        "target_id": {
          "name": "target_id",
          "type": "integer",
          "primaryKey": false,
          "notNull": true
        },
        "reason": {
          "name": "reason",
          "type": "text",
          "primaryKey": false,
          "notNull": true
        },
        "evidence": {
          "name": "evidence",
          "type": "jsonb",
          "primaryKey": false,
          "notNull": false
        },
        "created_at": {
          "name": "created_at",
          "type": "timestamp",
          "primaryKey": false,
          "notNull": true,
          "default": "now()"
        },
        "status": {
          "name": "status",
          "type": "varchar(32)",
          "primaryKey": false,
          "notNull": true,
          "default": "'open'"
        }
      },
      "indexes": {},
      "foreignKeys": {
        "reports_reporter_user_id_users_id_fk": {
          "name": "reports_reporter_user_id_users_id_fk",
          "tableFrom": "reports",
          "tableTo": "users",
          "columnsFrom": [
            "reporter_user_id"
          ],
          "columnsTo": [
            "id"
          ],
          "onDelete": "no action",
          "onUpdate": "no action"
        }
      },
      "compositePrimaryKeys": {},
      "uniqueConstraints": {}
    },
    "reservations": {
      "name": "reservations",
      "schema": "",
      "columns": {
        "id": {
          "name": "id",
          "type": "serial",
          "primaryKey": true,
          "notNull": true
        },
        "event_id": {
          "name": "event_id",
          "type": "integer",
          "primaryKey": false,
          "notNull": true
        },
        "user_id": {
          "name": "user_id",
          "type": "integer",
          "primaryKey": false,
          "notNull": true
        },
        "status": {
          "name": "status",
          "type": "reservation_status",
          "primaryKey": false,
          "notNull": true,
          "default": "'requested'"
        },
        "priority_score": {
          "name": "priority_score",
          "type": "integer",
          "primaryKey": false,
          "notNull": true,
          "default": 0
        },
        "payment_intent_id": {
          "name": "payment_intent_id",
          "type": "varchar(191)",
          "primaryKey": false,
          "notNull": false
        },
        "location_revealed_at": {
          "name": "location_revealed_at",
          "type": "timestamp",
          "primaryKey": false,
          "notNull": false
        }
      },
      "indexes": {},
      "foreignKeys": {
        "reservations_event_id_events_id_fk": {
          "name": "reservations_event_id_events_id_fk",
          "tableFrom": "reservations",
          "tableTo": "events",
          "columnsFrom": [
            "event_id"
          ],
          "columnsTo": [
            "id"
          ],
          "onDelete": "no action",
          "onUpdate": "no action"
        },
        "reservations_user_id_users_id_fk": {
          "name": "reservations_user_id_users_id_fk",
          "tableFrom": "reservations",
          "tableTo": "users",
          "columnsFrom": [
            "user_id"
          ],
          "columnsTo": [
            "id"
          ],
          "onDelete": "no action",
          "onUpdate": "no action"
        }
      },
      "compositePrimaryKeys": {},
      "uniqueConstraints": {}
    },
    "shops": {
      "name": "shops",
      "schema": "",
      "columns": {
        "id": {
          "name": "id",
          "type": "serial",
          "primaryKey": true,
          "notNull": true
        },
        "owner_user_id": {
          "name": "owner_user_id",
          "type": "integer",
          "primaryKey": false,
          "notNull": true
        },
        "name": {
          "name": "name",
          "type": "varchar(200)",
          "primaryKey": false,
          "notNull": true
        },
        "description": {
          "name": "description",
          "type": "text",
          "primaryKey": false,
          "notNull": true,
          "default": "''"
        },
        "logo_url": {
          "name": "logo_url",
          "type": "text",
          "primaryKey": false,
          "notNull": false
        },
        "stripe_connect_account_id": {
          "name": "stripe_connect_account_id",
          "type": "varchar(191)",
          "primaryKey": false,
          "notNull": false
        },
        "payouts_enabled": {
          "name": "payouts_enabled",
          "type": "boolean",
          "primaryKey": false,
          "notNull": true,
          "default": false
        },
        "status": {
          "name": "status",
          "type": "varchar(32)",
          "primaryKey": false,
          "notNull": true,
          "default": "'pending'"
        },
        "verified": {
          "name": "verified",
          "type": "boolean",
          "primaryKey": false,
          "notNull": true,
          "default": false
        }
      },
      "indexes": {},
      "foreignKeys": {
        "shops_owner_user_id_users_id_fk": {
          "name": "shops_owner_user_id_users_id_fk",
          "tableFrom": "shops",
          "tableTo": "users",
          "columnsFrom": [
            "owner_user_id"
          ],
          "columnsTo": [
            "id"
          ],
          "onDelete": "no action",
          "onUpdate": "no action"
        }
      },
      "compositePrimaryKeys": {},
      "uniqueConstraints": {}
    },
    "subscriptions": {
      "name": "subscriptions",
      "schema": "",
      "columns": {
        "user_id": {
          "name": "user_id",
          "type": "integer",
          "primaryKey": true,
          "notNull": true
        },
        "stripe_customer_id": {
          "name": "stripe_customer_id",
          "type": "varchar(191)",
          "primaryKey": false,
          "notNull": true
        },
        "stripe_subscription_id": {
          "name": "stripe_subscription_id",
          "type": "varchar(191)",
          "primaryKey": false,
          "notNull": true
        },
        "plan": {
          "name": "plan",
          "type": "varchar(100)",
          "primaryKey": false,
          "notNull": true
        },
        "status": {
          "name": "status",
          "type": "varchar(64)",
          "primaryKey": false,
          "notNull": true
        },
        "current_period_end": {
          "name": "current_period_end",
          "type": "timestamp",
          "primaryKey": false,
          "notNull": false
        }
      },
      "indexes": {},
      "foreignKeys": {
        "subscriptions_user_id_users_id_fk": {
          "name": "subscriptions_user_id_users_id_fk",
          "tableFrom": "subscriptions",
          "tableTo": "users",
          "columnsFrom": [
            "user_id"
          ],
          "columnsTo": [
            "id"
          ],
          "onDelete": "no action",
          "onUpdate": "no action"
        }
      },
      "compositePrimaryKeys": {},
      "uniqueConstraints": {}
    },
    "threads": {
      "name": "threads",
      "schema": "",
      "columns": {
        "id": {
          "name": "id",
          "type": "serial",
          "primaryKey": true,
          "notNull": true
        },
        "participant_a_id": {
          "name": "participant_a_id",
          "type": "integer",
          "primaryKey": false,
          "notNull": true
        },
        "participant_b_id": {
          "name": "participant_b_id",
          "type": "integer",
          "primaryKey": false,
          "notNull": true
        },
        "created_at": {
          "name": "created_at",
          "type": "timestamp",
          "primaryKey": false,
          "notNull": true,
          "default": "now()"
        }
      },
      "indexes": {},
      "foreignKeys": {
        "threads_participant_a_id_users_id_fk": {
          "name": "threads_participant_a_id_users_id_fk",
          "tableFrom": "threads",
          "tableTo": "users",
          "columnsFrom": [
            "participant_a_id"
          ],
          "columnsTo": [
            "id"
          ],
          "onDelete": "no action",
          "onUpdate": "no action"
        },
        "threads_participant_b_id_users_id_fk": {
          "name": "threads_participant_b_id_users_id_fk",
          "tableFrom": "threads",
          "tableTo": "users",
          "columnsFrom": [
            "participant_b_id"
          ],
          "columnsTo": [
            "id"
          ],
          "onDelete": "no action",
          "onUpdate": "no action"
        }
      },
      "compositePrimaryKeys": {},
      "uniqueConstraints": {}
    },
    "users": {
      "name": "users",
      "schema": "",
      "columns": {
        "id": {
          "name": "id",
          "type": "serial",
          "primaryKey": true,
          "notNull": true
        },
        "clerk_user_id": {
          "name": "clerk_user_id",
          "type": "varchar(191)",
          "primaryKey": false,
          "notNull": true
        },
        "admin_role": {
          "name": "admin_role",
          "type": "varchar(32)",
          "primaryKey": false,
          "notNull": true,
          "default": "'none'"
        },
        "account_type": {
          "name": "account_type",
          "type": "account_type",
          "primaryKey": false,
          "notNull": true
        },
        "display_name": {
          "name": "display_name",
          "type": "varchar(100)",
          "primaryKey": false,
          "notNull": true
        },
        "date_of_birth": {
          "name": "date_of_birth",
          "type": "timestamp",
          "primaryKey": false,
          "notNull": false
        },
        "age_verified_at": {
          "name": "age_verified_at",
          "type": "timestamp",
          "primaryKey": false,
          "notNull": false
        },
        "verification_level": {
          "name": "verification_level",
          "type": "verification_level",
          "primaryKey": false,
          "notNull": true,
          "default": "'none'"
        },
        "onboarding_complete": {
          "name": "onboarding_complete",
          "type": "boolean",
          "primaryKey": false,
          "notNull": true,
          "default": false
        },
        "subscription_tier": {
          "name": "subscription_tier",
          "type": "subscription_tier",
          "primaryKey": false,
          "notNull": false,
          "default": "'free'"
        },
        "is_vip": {
          "name": "is_vip",
          "type": "boolean",
          "primaryKey": false,
          "notNull": true,
          "default": false
        },
        "public_key": {
          "name": "public_key",
          "type": "text",
          "primaryKey": false,
          "notNull": false
        },
        "created_at": {
          "name": "created_at",
          "type": "timestamp",
          "primaryKey": false,
          "notNull": true,
          "default": "now()"
        },
        "updated_at": {
          "name": "updated_at",
          "type": "timestamp",
          "primaryKey": false,
          "notNull": false
        },
        "deleted_at": {
          "name": "deleted_at",
          "type": "timestamp",
          "primaryKey": false,
          "notNull": false
        },
        "deleted_by": {
          "name": "deleted_by",
          "type": "varchar(191)",
          "primaryKey": false,
          "notNull": false
        }
      },
      "indexes": {},
      "foreignKeys": {},
      "compositePrimaryKeys": {},
      "uniqueConstraints": {
        "users_clerk_user_id_unique": {
          "name": "users_clerk_user_id_unique",
          "nullsNotDistinct": false,
          "columns": [
            "clerk_user_id"
          ]
        }
      }
    },
    "verifications": {
      "name": "verifications",
      "schema": "",
      "columns": {
        "id": {
          "name": "id",
          "type": "serial",
          "primaryKey": true,
          "notNull": true
        },
        "user_id": {
          "name": "user_id",
          "type": "integer",
          "primaryKey": false,
          "notNull": true
        },
        "type": {
          "name": "type",
          "type": "varchar(32)",
          "primaryKey": false,
          "notNull": true
        },
        "status": {
          "name": "status",
          "type": "varchar(32)",
          "primaryKey": false,
          "notNull": true,
          "default": "'pending'"
        },
        "reviewed_by": {
          "name": "reviewed_by",
          "type": "integer",
          "primaryKey": false,
          "notNull": false
        },
        "evidence_ref": {
          "name": "evidence_ref",
          "type": "text",
          "primaryKey": false,
          "notNull": false
        },
        "reviewed_at": {
          "name": "reviewed_at",
          "type": "timestamp",
          "primaryKey": false,
          "notNull": false
        },
        "created_at": {
          "name": "created_at",
          "type": "timestamp",
          "primaryKey": false,
          "notNull": true,
          "default": "now()"
        }
      },
      "indexes": {},
      "foreignKeys": {
        "verifications_user_id_users_id_fk": {
          "name": "verifications_user_id_users_id_fk",
          "tableFrom": "verifications",
          "tableTo": "users",
          "columnsFrom": [
            "user_id"
          ],
          "columnsTo": [
            "id"
          ],
          "onDelete": "no action",
          "onUpdate": "no action"
        },
        "verifications_reviewed_by_users_id_fk": {
          "name": "verifications_reviewed_by_users_id_fk",
          "tableFrom": "verifications",
          "tableTo": "users",
          "columnsFrom": [
            "reviewed_by"
          ],
          "columnsTo": [
            "id"
          ],
          "onDelete": "no action",
          "onUpdate": "no action"
        }
      },
      "compositePrimaryKeys": {},
      "uniqueConstraints": {}
    }
  },
  "enums": {
    "account_type": {
      "name": "account_type",
      "values": {
        "FEMALE_SINGLE": "FEMALE_SINGLE",
        "MALE_SINGLE": "MALE_SINGLE",
        "COUPLE_MF": "COUPLE_MF",
        "COUPLE_MM": "COUPLE_MM",
        "COUPLE_FF": "COUPLE_FF",
        "SWING_CLUB": "SWING_CLUB",
        "SEX_SHOP": "SEX_SHOP"
      }
    },
    "csam_scan_status": {
      "name": "csam_scan_status",
      "values": {
        "pending": "pending",
        "clean": "clean",
        "flagged": "flagged",
        "error": "error",
        "unscanned": "unscanned"
      }
    },
    "moderation_status": {
      "name": "moderation_status",
      "values": {
        "pending": "pending",
        "approved": "approved",
        "rejected": "rejected"
      }
    },
    "order_status": {
      "name": "order_status",
      "values": {
        "pending": "pending",
        "paid": "paid",
        "shipped": "shipped",
        "delivered": "delivered",
        "refunded": "refunded",
        "cancelled": "cancelled"
      }
    },
    "push_platform": {
      "name": "push_platform",
      "values": {
        "web": "web",
        "expo": "expo"
      }
    },
    "reservation_status": {
      "name": "reservation_status",
      "values": {
        "requested": "requested",
        "accepted": "accepted",
        "declined": "declined",
        "waitlist": "waitlist"
      }
    },
    "subscription_tier": {
      "name": "subscription_tier",
      "values": {
        "free": "free",
        "vip": "vip"
      }
    },
    "verification_level": {
      "name": "verification_level",
      "values": {
        "none": "none",
        "photo": "photo",
        "video": "video",
        "social": "social"
      }
    }
  },
  "schemas": {},
  "_meta": {
    "columns": {},
    "schemas": {},
    "tables": {}
  }
}